{"sections":{"pf-5d15ab81":{"type":"pf-5d15ab81","settings":{}},"0e525f2c-a2b8-4a73-a663-f86083aa3fb2":{"type":"collection-list","blocks":{"template--20752949772577__0e525f2c-a2b8-4a73-a663-f86083aa3fb2-collection-1":{"type":"collection","settings":{"collection":"dash-cam","image":"shopify:\/\/shop_images\/800A.jpg","subheading":"","title":"","url":"","heading_tag":"h2","text_position":"place-self-center text-center","text_color":"#ffffff","overlay_color":"#000000","overlay_opacity":20}},"template--20752949772577__0e525f2c-a2b8-4a73-a663-f86083aa3fb2-collection-2":{"type":"collection","settings":{"collection":"accessories","image":"shopify:\/\/shop_images\/51OWFBaYMEL.jpg","subheading":"","title":"Dash Cam Accessories","url":"","heading_tag":"h2","text_position":"place-self-center text-center","text_color":"#ffffff","overlay_color":"#000000","overlay_opacity":20}},"template--20752949772577__0e525f2c-a2b8-4a73-a663-f86083aa3fb2-collection-3":{"type":"collection","settings":{"collection":"3w-floor-mats","image":"shopify:\/\/shop_images\/8_627c6eb0-5f04-4630-9a92-8d28fec3eba9.jpg","subheading":"","title":"Perfect Fit Floor Mats","url":"","heading_tag":"h2","text_position":"place-self-center text-center","text_color":"#ffffff","overlay_color":"#000000","overlay_opacity":20}}},"block_order":["template--20752949772577__0e525f2c-a2b8-4a73-a663-f86083aa3fb2-collection-1","template--20752949772577__0e525f2c-a2b8-4a73-a663-f86083aa3fb2-collection-2","template--20752949772577__0e525f2c-a2b8-4a73-a663-f86083aa3fb2-collection-3"],"settings":{"full_width":true,"stack_collections":true,"collections_per_row":3,"show_progress_bar":false,"subheading":"","title":"Discover More","content":"","link_url":"","link_text":"","background":"","background_gradient":"","text_color":"","heading_color":"","heading_gradient":""}}},"order":["pf-5d15ab81","0e525f2c-a2b8-4a73-a663-f86083aa3fb2"]}